harlow_bindicator/__init__.py
harlow_bindicator/api.py
harlow_bindicator/bindicator.py
harlow_bindicator/browser.py
harlow_bindicator/data.py
harlow_bindicator/main.py
harlow_bindicator/page_parser.py
harlow_bindicator-3.1.1.dist-info/LICENSE
harlow_bindicator-3.1.1.dist-info/METADATA
harlow_bindicator-3.1.1.dist-info/WHEEL
harlow_bindicator-3.1.1.dist-info/entry_points.txt
harlow_bindicator-3.1.1.dist-info/RECORD
