Metadata-Version: 2.3
Name: harlow-bindicator
Version: 3.1.1
Summary: Send alert the day before and on the day of bin collection in Harlow
License: MIT
Author: Joe McCarthy
Author-email: 179146301+joe-mccarthy@users.noreply.github.com
Maintainer: Joe McCarthy
Maintainer-email: 179146301+joe-mccarthy@users.noreply.github.com
Requires-Python: >=3.12,<4.0
Classifier: License :: OSI Approved :: MIT License
Classifier: Programming Language :: Python :: 3
Classifier: Programming Language :: Python :: 3.12
Classifier: Programming Language :: Python :: 3.13
Requires-Dist: beautifulsoup4 (>=4.12.3,<5.0.0)
Requires-Dist: requests (>=2.32.3,<3.0.0)
Requires-Dist: selenium (>=4.27.1,<5.0.0)
Project-URL: Documentation, https://github.com/joe-mccarthy/harlow-bindicator
Project-URL: Homepage, https://github.com/joe-mccarthy/harlow-bindicator
Project-URL: Repository, https://github.com/joe-mccarthy/harlow-bindicator
